library_simulator/__init__.py
library_simulator/data.py
library_simulator/generator.py
library_simulator/simulator.py
library_simulator/util.py
library_simulator/mutation_spectra/empirical.csv
library_simulator/mutation_spectra/flat.csv
library_simulator/mutation_spectra/published.csv
library_simulator-0.1.dist-info/LICENSE
library_simulator-0.1.dist-info/METADATA
library_simulator-0.1.dist-info/WHEEL
library_simulator-0.1.dist-info/top_level.txt
library_simulator-0.1.dist-info/RECORD
