Metadata-Version: 2.1
Name: library-simulator
Version: 0.1
Summary: Python software package for simulating random mutagenesis experiments
Home-page: https://github.com/harmslab/library_simulator
Author: Michael J. Harms
Author-email: harmsm@gmail.com
License: UNKNOWN
Download-URL: https://github.com/harmslab/library_simulator/archive/v0.1.tar.gz
Platform: UNKNOWN
Classifier: Programming Language :: Python
Requires-Dist: matplotlib
Requires-Dist: scipy
Requires-Dist: numpy
